CHANGES.rst
CONTRIBUTORS.rst
MANIFEST.in
README.rst
bootstrap.py
buildout.cfg
setup.py
travis.cfg
docs/LICENSE.GPL
docs/LICENSE.rst
src/collective/__init__.py
src/collective.badge.egg-info/PKG-INFO
src/collective.badge.egg-info/SOURCES.txt
src/collective.badge.egg-info/dependency_links.txt
src/collective.badge.egg-info/entry_points.txt
src/collective.badge.egg-info/namespace_packages.txt
src/collective.badge.egg-info/not-zip-safe
src/collective.badge.egg-info/requires.txt
src/collective.badge.egg-info/top_level.txt
src/collective/badge/__init__.py
src/collective/badge/api.py
src/collective/badge/configure.zcml
src/collective/badge/content.py
src/collective/badge/interfaces.py
src/collective/badge/testing.py
src/collective/badge/workspace.py
src/collective/badge/models/__init__.py
src/collective/badge/models/badge.xml
src/collective/badge/profiles/default/metadata.xml
src/collective/badge/profiles/default/types.xml
src/collective/badge/profiles/default/types/Badge.xml
src/collective/badge/templates/badge_view.pt
src/collective/badge/templates/leadimage-viewlet.pt
src/collective/badge/tests/__init__.py
src/collective/badge/tests/test_badge.py
src/collective/badge/tests/test_example.py