Metadata-Version: 1.1
Name: collective.badge
Version: 1.0.1
Summary: A basic member badge system for Plone
Home-page: https://github.com/collective/collective.badge
Author: David Glick
Author-email: david@glicksoftware.com
License: GPL
Keywords: plone badge
Platform: UNKNOWN
Classifier: Environment :: Web Environment
Classifier: Framework :: Plone
Classifier: Framework :: Plone :: 5.0
Classifier: Framework :: Plone :: 5.1
Classifier: Operating System :: OS Independent
Classifier: Programming Language :: Python
Classifier: Programming Language :: Python :: 2.6
Classifier: Programming Language :: Python :: 2.7
Classifier: Topic :: Software Development :: Libraries :: Python Modules
